{
    "report": [
        {
            "Name": "Костина Василиса",
            "Number": "89001115500",
            "Category": "Работа",
            "Comment": "Банк"
        },
        {
            "Name": "Кольцов Александр",
            "Number": "89001115501",
            "Category": "Друзья",
            "Comment": ""
        },
        {
            "Name": "Михайлов Дмитрий",
            "Number": "89001115502",
            "Category": "Семья",
            "Comment": ""
        },
        {
            "Name": "Васильев Дмитрий",
            "Number": "89001115503",
            "Category": "Учёба",
            "Comment": "Школа"
        },
        {
            "Name": "Трошин Святослав",
            "Number": "89001115504",
            "Category": "Не определено",
            "Comment": ""
        },
        {
            "Name": "Медведева Татьяна",
            "Number": "89001115505",
            "Category": "Работа",
            "Comment": ""
        },
        {
            "Name": "Шишкин Михаил",
            "Number": "89001115506",
            "Category": "Друзья",
            "Comment": ""
        },
        {
            "Name": "Виноградов Марсель",
            "Number": "89001115507",
            "Category": "Семья",
            "Comment": ""
        },
        {
            "Name": "Артемов Владислав",
            "Number": "89001115508",
            "Category": "Учёба",
            "Comment": "Университет"
        },
        {
            "Name": "Горбунов Владимир",
            "Number": "89001115509",
            "Category": "Не определено",
            "Comment": "Адвокат"
        },
        {
            "Name": "Петрова Полина",
            "Number": "89001115510",
            "Category": "Работа",
            "Comment": "Рекламное агентство"
        },
        {
            "Name": "Кулешова София",
            "Number": "89001115511",
            "Category": "Друзья",
            "Comment": ""
        },
        {
            "Name": "Беляков Леонид",
            "Number": "89001115512",
            "Category": "Семья",
            "Comment": ""
        },
        {
            "Name": "Кудрявцева Валерия",
            "Number": "89001115513",
            "Category": "Учёба",
            "Comment": "Университет"
        },
        {
            "Name": "Гусева Варвара",
            "Number": "89001115514",
            "Category": "Не определено",
            "Comment": ""
        },
        {
            "Name": "Бородин Демьян",
            "Number": "89001115515",
            "Category": "Работа",
            "Comment": "Рекламное агентство"
        },
        {
            "Name": "Касаткина Аделина",
            "Number": "89001115516",
            "Category": "Друзья",
            "Comment": ""
        },
        {
            "Name": "Филатов Дмитрий",
            "Number": "89001115517",
            "Category": "Семья",
            "Comment": ""
        },
        {
            "Name": "Тимофеева Кристина",
            "Number": "89001115518",
            "Category": "Учёба",
            "Comment": "Курсы"
        },
        {
            "Name": "Власова Алиса",
            "Number": "89001115519",
            "Category": "Не определено",
            "Comment": "Сантехник"
        },
        {
            "Name": "Семенова Варвара",
            "Number": "89001115520",
            "Category": "Работа",
            "Comment": "Банк"
        },
        {
            "Name": "Константинова Анна",
            "Number": "89001115521",
            "Category": "Друзья",
            "Comment": ""
        },
        {
            "Name": "Сергеева Василиса",
            "Number": "89001115522",
            "Category": "Семья",
            "Comment": ""
        },
        {
            "Name": "Лазарева Дарья",
            "Number": "89001115523",
            "Category": "Учёба",
            "Comment": "Английский"
        },
        {
            "Name": "Петрова Алиса",
            "Number": "89001115524",
            "Category": "Не определено",
            "Comment": ""
        },
        {
            "Name": "Медведева Мария",
            "Number": "89001115525",
            "Category": "Работа",
            "Comment": ""
        },
        {
            "Name": "Васильева Анастасия",
            "Number": "89001115526",
            "Category": "Друзья",
            "Comment": ""
        }
    ]
}